cccy/__init__.py
cccy/__main__.py
cccy/py.typed
cccy/application/__init__.py
cccy/application/interfaces/__init__.py
cccy/application/services/__init__.py
cccy/application/services/analysis_service.py
cccy/application/services/cli_facade_service.py
cccy/domain/__init__.py
cccy/domain/entities/__init__.py
cccy/domain/entities/complexity.py
cccy/domain/exceptions/__init__.py
cccy/domain/exceptions/complexity_exceptions.py
cccy/domain/interfaces/__init__.py
cccy/domain/interfaces/calculators.py
cccy/domain/interfaces/cli_services.py
cccy/domain/services/__init__.py
cccy/domain/services/complexity_analyzer.py
cccy/infrastructure/__init__.py
cccy/infrastructure/calculators/__init__.py
cccy/infrastructure/calculators/concrete_calculators.py
cccy/infrastructure/config/__init__.py
cccy/infrastructure/config/loaders.py
cccy/infrastructure/config/manager.py
cccy/infrastructure/config/merger.py
cccy/infrastructure/formatters/__init__.py
cccy/infrastructure/formatters/output.py
cccy/infrastructure/logging/__init__.py
cccy/infrastructure/logging/config.py
cccy/presentation/__init__.py
cccy/presentation/cli/__init__.py
cccy/presentation/cli/banner.py
cccy/presentation/cli/common.py
cccy/presentation/cli/helpers.py
cccy/presentation/cli/main.py
cccy/presentation/factories/__init__.py
cccy/presentation/factories/service_factory.py
cccy/shared/__init__.py
cccy/shared/type_helpers.py
cccy-0.2.1.dist-info/METADATA
cccy-0.2.1.dist-info/WHEEL
cccy-0.2.1.dist-info/entry_points.txt
cccy-0.2.1.dist-info/RECORD
