Metadata-Version: 2.4
Name: cccy
Version: 0.2.1
Summary: Python complexity measurement tool
Project-URL: Homepage, https://github.com/mmocchi/cccy
Project-URL: Repository, https://github.com/mmocchi/cccy
Project-URL: Issues, https://github.com/mmocchi/cccy/issues
Author-email: mmocchi <akihiro.matsumoto.exe@gmail.com>
License-Expression: MIT
Classifier: Development Status :: 4 - Beta
Classifier: Intended Audience :: Developers
Classifier: License :: OSI Approved :: MIT License
Classifier: Programming Language :: Python :: 3
Classifier: Programming Language :: Python :: 3.9
Classifier: Programming Language :: Python :: 3.10
Classifier: Programming Language :: Python :: 3.11
Classifier: Programming Language :: Python :: 3.12
Classifier: Programming Language :: Python :: 3.13
Classifier: Topic :: Software Development :: Quality Assurance
Requires-Python: >=3.9
Requires-Dist: click>=8.0.0
Requires-Dist: cognitive-complexity>=1.3.0
Requires-Dist: mccabe>=0.7.0
Requires-Dist: pydantic-settings>=2.0.0
Requires-Dist: pydantic>=2.0.0
Requires-Dist: tabulate>=0.9.0
Requires-Dist: tomli>=1.2.0; python_version < '3.11'
